satellites/__init__.py
satellites/_version.py
satellites/handlers.py
satellites/tests/__init__.py
satellites/tests/test_handlers.py
satellites-0.0.2.data/data/etc/jupyter/jupyter_notebook_config.d/satellites.json
satellites-0.0.2.data/data/etc/jupyter/jupyter_server_config.d/satellites.json
satellites-0.0.2.data/data/share/jupyter/labextensions/@datalayer/satellites/build_log.json
satellites-0.0.2.data/data/share/jupyter/labextensions/@datalayer/satellites/package.json
satellites-0.0.2.data/data/share/jupyter/labextensions/@datalayer/satellites/schemas/@datalayer/satellites/package.json.orig
satellites-0.0.2.data/data/share/jupyter/labextensions/@datalayer/satellites/schemas/@datalayer/satellites/plugin.json
satellites-0.0.2.data/data/share/jupyter/labextensions/@datalayer/satellites/static/design_icons_lib_index_js.5bf511ee353de174333c.js
satellites-0.0.2.data/data/share/jupyter/labextensions/@datalayer/satellites/static/design_icons_lib_index_js.5bf511ee353de174333c.js.map
satellites-0.0.2.data/data/share/jupyter/labextensions/@datalayer/satellites/static/lib_index_js.611c7144fa7dc7b767a3.js
satellites-0.0.2.data/data/share/jupyter/labextensions/@datalayer/satellites/static/lib_index_js.611c7144fa7dc7b767a3.js.map
satellites-0.0.2.data/data/share/jupyter/labextensions/@datalayer/satellites/static/remoteEntry.302111f2cb3d1eb51657.js
satellites-0.0.2.data/data/share/jupyter/labextensions/@datalayer/satellites/static/remoteEntry.302111f2cb3d1eb51657.js.map
satellites-0.0.2.data/data/share/jupyter/labextensions/@datalayer/satellites/static/style.js
satellites-0.0.2.data/data/share/jupyter/labextensions/@datalayer/satellites/static/style_index_js.e8faaf8db464822d66eb.js
satellites-0.0.2.data/data/share/jupyter/labextensions/@datalayer/satellites/static/style_index_js.e8faaf8db464822d66eb.js.map
satellites-0.0.2.dist-info/METADATA
satellites-0.0.2.dist-info/WHEEL
satellites-0.0.2.dist-info/licenses/LICENSE
satellites-0.0.2.dist-info/RECORD
